rosetta_ai/__init__.py
rosetta_ai/py.typed
rosetta_ai-0.1.0.dist-info/METADATA
rosetta_ai-0.1.0.dist-info/WHEEL
rosetta_ai-0.1.0.dist-info/licenses/LICENSE
rosetta_ai-0.1.0.dist-info/RECORD
