Metadata-Version: 2.4
Name: rosetta-ai
Version: 0.1.0
Summary: The translation layer for LLM provider messages
Project-URL: repository, https://github.com/latitude-dev/rosetta-py
Project-URL: homepage, https://github.com/latitude-dev/rosetta-py#readme
Project-URL: documentation, https://github.com/latitude-dev/rosetta-py#readme
Author-email: Latitude Data SL <hello@latitude.so>
Maintainer-email: Latitude Data SL <hello@latitude.so>
License-Expression: MIT
License-File: LICENSE
Requires-Python: <3.14,>=3.9
